requests_toolkit/__init__.py
requests_toolkit/_abstracts_arxiv.py
requests_toolkit/_academic.py
requests_toolkit/_air_quality.py
requests_toolkit/_exchange_rate_cn.py
requests_toolkit/_inferenceHF.py
requests_toolkit/_realpython_news.py
requests_toolkit/_thesis_info.py
requests_toolkit/_weather_query.py
requests_toolkit/_ytb_channel_info.py
requests_toolkit/utils.py
requests_toolkit/asyncpy/__init__.py
requests_toolkit/asyncpy/http.py
requests_toolkit/asyncpy/loop.py
requests_toolkit/asyncpy/utils.py
requests_toolkit/asyncpy/hkcsr/__init__.py
requests_toolkit/asyncpy/hkcsr/_cuhk.py
requests_toolkit/gsheet/__init__.py
requests_toolkit/gsheet/_io.py
requests_toolkit/openpy/__init__.py
requests_toolkit/openpy/_openai.py
requests_toolkit/openpy/_return.py
requests_toolkit/openpy/config/__init__.py
requests_toolkit/openpy/config/_chatcompletion.py
requests_toolkit/threading/__init__.py
requests_toolkit/threading/loop.py
requests_toolkit/translate/__init__.py
requests_toolkit/translate/_engine.py
requests_toolkit/translate/_language.py
requests_toolkit/translate/_translator.py
requests_toolkit_stable-0.26.3.dist-info/LICENSE
requests_toolkit_stable-0.26.3.dist-info/METADATA
requests_toolkit_stable-0.26.3.dist-info/WHEEL
requests_toolkit_stable-0.26.3.dist-info/top_level.txt
requests_toolkit_stable-0.26.3.dist-info/RECORD
