Metadata-Version: 2.1
Name: requests-toolkit-stable
Version: 0.26.3
Summary: A package of APIs using requests.
Home-page: https://github.com/leoxiang66/requests-toolkit
Author: Tao Xiang
Author-email: tao.xiang@tum.de
License: UNKNOWN
Platform: UNKNOWN
Classifier: Programming Language :: Python :: 3.10
Classifier: License :: OSI Approved :: MIT License
License-File: LICENSE
Requires-Dist: lxml
Requires-Dist: requests
Requires-Dist: xmltodict
Requires-Dist: tqdm
Requires-Dist: aiohttp ==3.8.3
Requires-Dist: pandas
Requires-Dist: openai ==0.27.0
Requires-Dist: shillelagh ==1.1.5
Requires-Dist: shillelagh[gsheetsapi]
Requires-Dist: beautifulsoup4 ==4.12.3
